WaporAPI/Collect.py
WaporAPI/__init__.py
WaporAPI-0.0.3.dist-info/LICENSE
WaporAPI-0.0.3.dist-info/METADATA
WaporAPI-0.0.3.dist-info/WHEEL
WaporAPI-0.0.3.dist-info/top_level.txt
WaporAPI-0.0.3.dist-info/RECORD
