Metadata-Version: 2.1
Name: WaporAPI
Version: 0.0.3
Summary: Tool for collecting WaPOR dataset automatically through python.
Home-page: https://github.com/TimHessels/WaporAPI
Author: Tim Hessels
Author-email: timhessels@hotmail.com
License: UNKNOWN
Platform: UNKNOWN
Classifier: Programming Language :: Python :: 3
Classifier: License :: OSI Approved :: Apache Software License
Classifier: Operating System :: OS Independent
